README.md
setup.py
pulumi_aws_iam/__init__.py
pulumi_aws_iam/_inputs.py
pulumi_aws_iam/_utilities.py
pulumi_aws_iam/account.py
pulumi_aws_iam/assumable_role.py
pulumi_aws_iam/assumable_role_with_oidc.py
pulumi_aws_iam/assumable_role_with_saml.py
pulumi_aws_iam/assumable_roles.py
pulumi_aws_iam/assumable_roles_with_saml.py
pulumi_aws_iam/eks_role.py
pulumi_aws_iam/group_with_assumable_roles_policy.py
pulumi_aws_iam/group_with_policies.py
pulumi_aws_iam/outputs.py
pulumi_aws_iam/policy.py
pulumi_aws_iam/provider.py
pulumi_aws_iam/pulumi-plugin.json
pulumi_aws_iam/py.typed
pulumi_aws_iam/read_only_policy.py
pulumi_aws_iam/role_for_service_accounts_eks.py
pulumi_aws_iam/user.py
pulumi_aws_iam.egg-info/PKG-INFO
pulumi_aws_iam.egg-info/SOURCES.txt
pulumi_aws_iam.egg-info/dependency_links.txt
pulumi_aws_iam.egg-info/not-zip-safe
pulumi_aws_iam.egg-info/requires.txt
pulumi_aws_iam.egg-info/top_level.txt